flask_alembic/__init__.py
flask_alembic/cli.py
flask_alembic/extension.py
flask_alembic/py.typed
flask_alembic-3.0.0.dist-info/LICENSE.txt
flask_alembic-3.0.0.dist-info/WHEEL
flask_alembic-3.0.0.dist-info/METADATA
flask_alembic-3.0.0.dist-info/RECORD
