Metadata-Version: 2.1
Name: Flask-Alembic
Version: 3.0.0
Summary: Flask extension to integrate Alembic with Flask-SQLAlchemy.
Author-email: David Lord <davidism@gmail.com>
Requires-Python: >=3.8
Classifier: Development Status :: 5 - Production/Stable
Classifier: Environment :: Web Environment
Classifier: Framework :: Flask
Classifier: Intended Audience :: Developers
Classifier: License :: OSI Approved :: MIT License
Classifier: Operating System :: OS Independent
Classifier: Programming Language :: Python
Classifier: Topic :: Database
Classifier: Typing :: Typed
Requires-Dist: alembic>=1.13
Requires-Dist: flask>=3.0
Requires-Dist: flask-sqlalchemy>=3.1
Requires-Dist: sqlalchemy>=2.0
Project-URL: Changes, https://flask-alembic.readthedocs.io/changes/
Project-URL: Documentation, https://flask-alembic.readthedocs.io
Project-URL: Source, https://github.com/davidism/flask-alembic/
